[{"user_folder": "richey-c", "count": 582}, {"user_folder": "taylor-m", "count": 13875}, {"user_folder": "scholtes-d", "count": 647}, {"user_folder": "kean-s", "count": 25351}, {"user_folder": "ruscitti-k", "count": 1643}, {"user_folder": "brawner-s", "count": 1026}, {"user_folder": "kitchen-l", "count": 5546}, {"user_folder": "skilling-j", "count": 4139}, {"user_folder": "linder-e", "count": 2805}, {"user_folder": "keiser-k", "count": 1113}, {"user_folder": "schwieger-j", "count": 738}, {"user_folder": "kuykendall-t", "count": 1120}, {"user_folder": "williams-j", "count": 1213}, {"user_folder": "farmer-d", "count": 13032}, {"user_folder": "zipper-a", "count": 1563}, {"user_folder": "ybarbo-p", "count": 1291}, {"user_folder": "lokey-t", "count": 1156}, {"user_folder": "blair-l", "count": 3415}, {"user_folder": "heard-m", "count": 1623}, {"user_folder": "staab-t", "count": 621}, {"user_folder": "whitt-m", "count": 807}, {"user_folder": "mckay-j", "count": 998}, {"user_folder": "hodge-j", "count": 1661}, {"user_folder": "williams-w3", "count": 3440}, {"user_folder": "mcconnell-m", "count": 4542}, {"user_folder": "guzman-m", "count": 6054}, {"user_folder": "thomas-p", "count": 1293}, {"user_folder": "harris-s", "count": 548}, {"user_folder": "semperger-c", "count": 721}, {"user_folder": "shackleton-s", "count": 18687}, {"user_folder": "buy-r", "count": 2429}, {"user_folder": "stepenovitch-j", "count": 1227}, {"user_folder": "crandell-s", "count": 519}, {"user_folder": "pereira-s", "count": 725}, {"user_folder": "giron-d", "count": 4220}, {"user_folder": "benson-r", "count": 767}, {"user_folder": "fischer-m", "count": 1498}, {"user_folder": "keavey-p", "count": 2177}, {"user_folder": "may-l", "count": 1600}, {"user_folder": "pimenov-v", "count": 642}, {"user_folder": "stclair-c", "count": 3030}, {"user_folder": "shively-h", "count": 1991}, {"user_folder": "corman-s", "count": 2025}, {"user_folder": "mckay-b", "count": 681}, {"user_folder": "geaccone-t", "count": 1592}, {"user_folder": "fossum-d", "count": 4796}, {"user_folder": "gilbertsmith-d", "count": 578}, {"user_folder": "martin-t", "count": 1112}, {"user_folder": "steffes-j", "count": 3331}, {"user_folder": "gay-r", "count": 1415}, {"user_folder": "panus-s", "count": 437}, {"user_folder": "gang-l", "count": 590}, {"user_folder": "mann-k", "count": 23381}, {"user_folder": "ermis-f", "count": 1230}, {"user_folder": "ring-r", "count": 994}, {"user_folder": "tycholiz-b", "count": 1219}, {"user_folder": "parks-j", "count": 2284}, {"user_folder": "rapp-b", "count": 563}, {"user_folder": "sanders-r", "count": 7329}, {"user_folder": "ward-k", "count": 2611}, {"user_folder": "derrick-j", "count": 1766}, {"user_folder": "shapiro-r", "count": 6071}, {"user_folder": "solberg-g", "count": 1081}, {"user_folder": "perlingiere-d", "count": 4778}, {"user_folder": "cash-m", "count": 2969}, {"user_folder": "shankman-j", "count": 3856}, {"user_folder": "dasovich-j", "count": 28234}, {"user_folder": "zufferli-j", "count": 557}, {"user_folder": "reitmeyer-j", "count": 498}, {"user_folder": "sager-e", "count": 5200}, {"user_folder": "hyvl-d", "count": 3210}, {"user_folder": "lavorato-j", "count": 4685}, {"user_folder": "phanis-s", "count": 35}, {"user_folder": "grigsby-m", "count": 2237}, {"user_folder": "delainey-d", "count": 3566}, {"user_folder": "germany-c", "count": 12436}, {"user_folder": "griffith-j", "count": 2973}, {"user_folder": "lokay-m", "count": 5568}, {"user_folder": "kaminski-v", "count": 28465}, {"user_folder": "arnold-j", "count": 4898}, {"user_folder": "lewis-a", "count": 2191}, {"user_folder": "mccarty-d", "count": 691}, {"user_folder": "forney-j", "count": 729}, {"user_folder": "townsend-j", "count": 646}, {"user_folder": "scott-s", "count": 8022}, {"user_folder": "whalley-g", "count": 1878}, {"user_folder": "whalley-l", "count": 3335}, {"user_folder": "wolfe-j", "count": 1587}, {"user_folder": "lay-k", "count": 5937}, {"user_folder": "king-j", "count": 462}, {"user_folder": "dean-c", "count": 2429}, {"user_folder": "love-p", "count": 5002}, {"user_folder": "dorland-c", "count": 2127}, {"user_folder": "saibi-e", "count": 1116}, {"user_folder": "schoolcraft-d", "count": 1859}, {"user_folder": "white-s", "count": 3272}, {"user_folder": "symes-k", "count": 10827}, {"user_folder": "lenhart-m", "count": 5920}, {"user_folder": "lucci-p", "count": 997}, {"user_folder": "ring-a", "count": 706}, {"user_folder": "presto-k", "count": 2204}, {"user_folder": "hernandez-j", "count": 3265}, {"user_folder": "hain-m", "count": 3820}, {"user_folder": "mclaughlin-e", "count": 3353}, {"user_folder": "sturm-f", "count": 1169}, {"user_folder": "neal-s", "count": 3268}, {"user_folder": "badeer-r", "count": 877}, {"user_folder": "storey-g", "count": 1027}, {"user_folder": "campbell-l", "count": 6490}, {"user_folder": "baughman-d", "count": 2760}, {"user_folder": "davis-d", "count": 2249}, {"user_folder": "bailey-s", "count": 478}, {"user_folder": "haedicke-m", "count": 5246}, {"user_folder": "rodrique-r", "count": 2766}, {"user_folder": "swerzbin-m", "count": 355}, {"user_folder": "maggi-m", "count": 1991}, {"user_folder": "watson-k", "count": 2950}, {"user_folder": "donohoe-t", "count": 1015}, {"user_folder": "jones-t", "count": 19950}, {"user_folder": "hendrickson-s", "count": 719}, {"user_folder": "merriss-s", "count": 1627}, {"user_folder": "weldon-c", "count": 1566}, {"user_folder": "mims-thurston-p", "count": 2038}, {"user_folder": "smith-m", "count": 1642}, {"user_folder": "stokley-c", "count": 1252}, {"user_folder": "hyatt-k", "count": 1794}, {"user_folder": "causholli-m", "count": 943}, {"user_folder": "platter-p", "count": 574}, {"user_folder": "motley-m", "count": 378}, {"user_folder": "nemec-g", "count": 10655}, {"user_folder": "allen-p", "count": 3034}, {"user_folder": "horton-s", "count": 2470}, {"user_folder": "meyers-a", "count": 1099}, {"user_folder": "salisbury-h", "count": 1632}, {"user_folder": "quenet-j", "count": 395}, {"user_folder": "bass-e", "count": 7823}, {"user_folder": "cuilla-m", "count": 1029}, {"user_folder": "hayslett-r", "count": 2554}, {"user_folder": "tholt-j", "count": 1885}, {"user_folder": "sanchez-m", "count": 256}, {"user_folder": "arora-h", "count": 654}, {"user_folder": "rogers-b", "count": 8009}, {"user_folder": "carson-m", "count": 1400}, {"user_folder": "slinger-r", "count": 132}, {"user_folder": "holst-k", "count": 463}, {"user_folder": "quigley-d", "count": 1568}, {"user_folder": "dickson-s", "count": 395}, {"user_folder": "donoho-l", "count": 1045}, {"user_folder": "beck-s", "count": 11830}, {"user_folder": "south-s", "count": 248}]
